vikingdb/__init__.py
vikingdb/_client.py
vikingdb/auth.py
vikingdb/exceptions.py
vikingdb/request_options.py
vikingdb/version.py
vikingdb/memory/__init__.py
vikingdb/memory/client.py
vikingdb/memory/collection.py
vikingdb/memory/exceptions.py
vikingdb/memory/types.py
vikingdb/vector/__init__.py
vikingdb/vector/base.py
vikingdb/vector/client.py
vikingdb/vector/collection.py
vikingdb/vector/embedding.py
vikingdb/vector/exceptions.py
vikingdb/vector/index.py
vikingdb/vector/rerank.py
vikingdb/vector/models/__init__.py
vikingdb/vector/models/base.py
vikingdb/vector/models/collection.py
vikingdb/vector/models/embedding.py
vikingdb/vector/models/index.py
vikingdb/vector/models/rerank.py
vikingdb_python_sdk-0.1.9.dist-info/licenses/LICENSE.txt
vikingdb_python_sdk-0.1.9.dist-info/METADATA
vikingdb_python_sdk-0.1.9.dist-info/WHEEL
vikingdb_python_sdk-0.1.9.dist-info/top_level.txt
vikingdb_python_sdk-0.1.9.dist-info/RECORD
