Metadata-Version: 2.4
Name: vikingdb-python-sdk
Version: 0.1.9
Summary: vikingdb Python SDK
License-Expression: Apache-2.0
Project-URL: Documentation, https://github.com/volcengine/volc-vikingdb-python-sdk/README.md
Project-URL: Source, https://github.com/volcengine/volc-vikingdb-python-sdk
Keywords: vikingdb,vector,bytedance,volcengine,sdk
Classifier: Development Status :: 4 - Beta
Classifier: Intended Audience :: Developers
Classifier: Programming Language :: Python :: 3
Classifier: Programming Language :: Python :: 3.8
Classifier: Programming Language :: Python :: 3.9
Classifier: Programming Language :: Python :: 3.10
Classifier: Programming Language :: Python :: 3.11
Classifier: Topic :: Software Development :: Libraries
Requires-Python: >=3.8
License-File: LICENSE.txt
Requires-Dist: httpx>=0.24.1
Requires-Dist: requests>=2.28.1
Requires-Dist: pydantic>=2.5.3
Requires-Dist: urllib3>=1.21.1
Requires-Dist: volcengine>=1.0.0
Requires-Dist: aiohttp>=3.10.0
Dynamic: license-file
